pytest_stepthrough/__init__.py
pytest_stepthrough/plugin.py
pytest_stepthrough-0.1.0.dist-info/licenses/LICENSE
pytest_stepthrough-0.1.0.dist-info/METADATA
pytest_stepthrough-0.1.0.dist-info/WHEEL
pytest_stepthrough-0.1.0.dist-info/entry_points.txt
pytest_stepthrough-0.1.0.dist-info/top_level.txt
pytest_stepthrough-0.1.0.dist-info/RECORD
