Metadata-Version: 2.4
Name: pytest-stepthrough
Version: 0.1.0
Summary: Pause and wait for Enter after each test with --step
Author: Your Name
License: MIT
Project-URL: Homepage, https://github.com/greg-baker-public/pytest-stepthrough
Project-URL: Repository, https://github.com/greg-baker-public/pytest-stepthrough
Project-URL: Issues, https://github.com/greg-baker-public/pytest-stepthrough/issues
Classifier: Programming Language :: Python :: 3
Classifier: Framework :: Pytest
Requires-Python: >=3.8
License-File: LICENSE
Dynamic: license-file
